cleanlab_tlm/__about__.py
cleanlab_tlm/__init__.py
cleanlab_tlm/errors.py
cleanlab_tlm/py.typed
cleanlab_tlm/tlm.py
cleanlab_tlm/internal/__init__.py
cleanlab_tlm/internal/base.py
cleanlab_tlm/internal/concurrency.py
cleanlab_tlm/internal/constants.py
cleanlab_tlm/internal/exception_handling.py
cleanlab_tlm/internal/rag.py
cleanlab_tlm/internal/types.py
cleanlab_tlm/internal/validation.py
cleanlab_tlm/internal/api/__init__.py
cleanlab_tlm/internal/api/api.py
cleanlab_tlm/utils/__init__.py
cleanlab_tlm/utils/chat.py
cleanlab_tlm/utils/chat_completions.py
cleanlab_tlm/utils/config.py
cleanlab_tlm/utils/per_field_score_utils.py
cleanlab_tlm/utils/rag.py
cleanlab_tlm/utils/responses.py
cleanlab_tlm/utils/tlm_calibrated.py
cleanlab_tlm/utils/tlm_lite.py
cleanlab_tlm/utils/vpc/__init__.py
cleanlab_tlm/utils/vpc/chat_completions.py
cleanlab_tlm/utils/vpc/tlm.py
cleanlab_tlm-1.1.38.dist-info/METADATA
cleanlab_tlm-1.1.38.dist-info/WHEEL
cleanlab_tlm-1.1.38.dist-info/licenses/LICENSE
cleanlab_tlm-1.1.38.dist-info/RECORD
